undefined/__init__.py
undefined/tests/test_undefined.py
undefined-0.0.8.dist-info/LICENSE
undefined-0.0.8.dist-info/WHEEL
undefined-0.0.8.dist-info/METADATA
undefined-0.0.8.dist-info/RECORD
