Metadata-Version: 2.1
Name: undefined
Version: 0.0.8
Summary: a simple package
Home-page: https://github.com/Carreau/undefined
License: UNKNOWN
Author: Matthias Bussonnier
Author-email: bussonniermatthias@gmail.com
Requires-Python: >=3.4
Classifier: License :: OSI Approved :: MIT License
